soma/__init__.py
soma/activate_virtualenv.py
soma/api.py
soma/application.py
soma/archive.py
soma/bufferandfile.py
soma/config.py
soma/crypt.py
soma/debug.py
soma/factory.py
soma/fom.py
soma/functiontools.py
soma/global_naming.py
soma/html.py
soma/importer.py
soma/info.py
soma/logging.py
soma/mpfork.py
soma/mpfork2.py
soma/notification.py
soma/path.py
soma/qimage2ndarray.py
soma/safemkdir.py
soma/serialization.py
soma/singleton.py
soma/somatime.py
soma/sorted_dictionary.py
soma/sqlite_tools.py
soma/stringtools.py
soma/subprocess.py
soma/thread_calls.py
soma/topological_sort.py
soma/translation.py
soma/undefined.py
soma/uuid.py
soma/controller/__init__.py
soma/controller/controller.py
soma/controller/factory.py
soma/controller/trait_utils.py
soma/controller/tests/__init__.py
soma/controller/tests/test_controller.py
soma/minf/__init__.py
soma/minf/api.py
soma/minf/error.py
soma/minf/reader.py
soma/minf/tree.py
soma/minf/writer.py
soma/minf/xhtml.py
soma/minf/xml_reader.py
soma/minf/xml_tags.py
soma/minf/xml_writer.py
soma/minf/tests/__init__.py
soma/minf/tests/test_minf_io.py
soma/pipeline/__init__.py
soma/pipeline/study.py
soma/plugins/__init__.py
soma/qt_gui/__init__.py
soma/qt_gui/controller_widget.py
soma/qt_gui/generic_table_editor.py
soma/qt_gui/headless.py
soma/qt_gui/io.py
soma/qt_gui/ipkernel_tools.py
soma/qt_gui/predef_lineedit.py
soma/qt_gui/qtThread.py
soma/qt_gui/qt_backend.py
soma/qt_gui/qvtabbar.py
soma/qt_gui/rangeSlider.py
soma/qt_gui/timered_widgets.py
soma/qt_gui/controls/Bool.py
soma/qt_gui/controls/Bytes.py
soma/qt_gui/controls/Compound.py
soma/qt_gui/controls/Controller.py
soma/qt_gui/controls/Dict.py
soma/qt_gui/controls/Directory.py
soma/qt_gui/controls/Enum.py
soma/qt_gui/controls/File.py
soma/qt_gui/controls/Float.py
soma/qt_gui/controls/Int.py
soma/qt_gui/controls/List.py
soma/qt_gui/controls/List_File_offscreen.py
soma/qt_gui/controls/List_offscreen.py
soma/qt_gui/controls/Str.py
soma/qt_gui/controls/__init__.py
soma_base-6.0.6.dist-info/METADATA
soma_base-6.0.6.dist-info/WHEEL
soma_base-6.0.6.dist-info/top_level.txt
soma_base-6.0.6.dist-info/RECORD
